{
  "container": {
    "length": 100,
    "width": 100,
    "height": 100
  },
  "size_name": "large",
  "num_items": 667,
  "items": [
    {
      "id": 0,
      "length": 12,
      "width": 44,
      "height": 42,
      "volume": 22176
    },
    {
      "id": 1,
      "length": 33,
      "width": 28,
      "height": 27,
      "volume": 24948
    },
    {
      "id": 2,
      "length": 33,
      "width": 44,
      "height": 10,
      "volume": 14520
    },
    {
      "id": 3,
      "length": 45,
      "width": 34,
      "height": 43,
      "volume": 65790
    },
    {
      "id": 4,
      "length": 34,
      "width": 25,
      "height": 43,
      "volume": 36550
    },
    {
      "id": 5,
      "length": 38,
      "width": 28,
      "height": 32,
      "volume": 34048
    },
    {
      "id": 6,
      "length": 28,
      "width": 34,
      "height": 25,
      "volume": 23800
    },
    {
      "id": 7,
      "length": 18,
      "width": 10,
      "height": 28,
      "volume": 5040
    },
    {
      "id": 8,
      "length": 42,
      "width": 43,
      "height": 25,
      "volume": 45150
    },
    {
      "id": 9,
      "length": 49,
      "width": 27,
      "height": 43,
      "volume": 56889
    },
    {
      "id": 10,
      "length": 34,
      "width": 15,
      "height": 30,
      "volume": 15300
    },
    {
      "id": 11,
      "length": 15,
      "width": 41,
      "height": 48,
      "volume": 29520
    },
    {
      "id": 12,
      "length": 40,
      "width": 19,
      "height": 39,
      "volume": 29640
    },
    {
      "id": 13,
      "length": 27,
      "width": 33,
      "height": 18,
      "volume": 16038
    },
    {
      "id": 14,
      "length": 40,
      "width": 24,
      "height": 13,
      "volume": 12480
    },
    {
      "id": 15,
      "length": 49,
      "width": 18,
      "height": 18,
      "volume": 15876
    },
    {
      "id": 16,
      "length": 35,
      "width": 13,
      "height": 26,
      "volume": 11830
    },
    {
      "id": 17,
      "length": 25,
      "width": 24,
      "height": 44,
      "volume": 26400
    },
    {
      "id": 18,
      "length": 14,
      "width": 14,
      "height": 29,
      "volume": 5684
    },
    {
      "id": 19,
      "length": 24,
      "width": 27,
      "height": 11,
      "volume": 7128
    },
    {
      "id": 20,
      "length": 38,
      "width": 22,
      "height": 13,
      "volume": 10868
    },
    {
      "id": 21,
      "length": 19,
      "width": 40,
      "height": 17,
      "volume": 12920
    },
    {
      "id": 22,
      "length": 12,
      "width": 18,
      "height": 39,
      "volume": 8424
    },
    {
      "id": 23,
      "length": 20,
      "width": 44,
      "height": 46,
      "volume": 40480
    },
    {
      "id": 24,
      "length": 22,
      "width": 45,
      "height": 22,
      "volume": 21780
    },
    {
      "id": 25,
      "length": 21,
      "width": 46,
      "height": 19,
      "volume": 18354
    },
    {
      "id": 26,
      "length": 18,
      "width": 16,
      "height": 11,
      "volume": 3168
    },
    {
      "id": 27,
      "length": 32,
      "width": 48,
      "height": 49,
      "volume": 75264
    },
    {
      "id": 28,
      "length": 48,
      "width": 30,
      "height": 32,
      "volume": 46080
    },
    {
      "id": 29,
      "length": 38,
      "width": 23,
      "height": 35,
      "volume": 30590
    },
    {
      "id": 30,
      "length": 14,
      "width": 40,
      "height": 34,
      "volume": 19040
    },
    {
      "id": 31,
      "length": 40,
      "width": 29,
      "height": 26,
      "volume": 30160
    },
    {
      "id": 32,
      "length": 11,
      "width": 34,
      "height": 22,
      "volume": 8228
    },
    {
      "id": 33,
      "length": 48,
      "width": 37,
      "height": 15,
      "volume": 26640
    },
    {
      "id": 34,
      "length": 12,
      "width": 44,
      "height": 27,
      "volume": 14256
    },
    {
      "id": 35,
      "length": 20,
      "width": 29,
      "height": 14,
      "volume": 8120
    },
    {
      "id": 36,
      "length": 28,
      "width": 31,
      "height": 28,
      "volume": 24304
    },
    {
      "id": 37,
      "length": 25,
      "width": 33,
      "height": 13,
      "volume": 10725
    },
    {
      "id": 38,
      "length": 24,
      "width": 34,
      "height": 44,
      "volume": 35904
    },
    {
      "id": 39,
      "length": 23,
      "width": 28,
      "height": 47,
      "volume": 30268
    },
    {
      "id": 40,
      "length": 45,
      "width": 16,
      "height": 39,
      "volume": 28080
    },
    {
      "id": 41,
      "length": 28,
      "width": 34,
      "height": 25,
      "volume": 23800
    },
    {
      "id": 42,
      "length": 49,
      "width": 17,
      "height": 27,
      "volume": 22491
    },
    {
      "id": 43,
      "length": 37,
      "width": 25,
      "height": 28,
      "volume": 25900
    },
    {
      "id": 44,
      "length": 26,
      "width": 22,
      "height": 16,
      "volume": 9152
    },
    {
      "id": 45,
      "length": 36,
      "width": 19,
      "height": 43,
      "volume": 29412
    },
    {
      "id": 46,
      "length": 45,
      "width": 34,
      "height": 15,
      "volume": 22950
    },
    {
      "id": 47,
      "length": 33,
      "width": 27,
      "height": 32,
      "volume": 28512
    },
    {
      "id": 48,
      "length": 15,
      "width": 38,
      "height": 34,
      "volume": 19380
    },
    {
      "id": 49,
      "length": 26,
      "width": 33,
      "height": 20,
      "volume": 17160
    },
    {
      "id": 50,
      "length": 35,
      "width": 43,
      "height": 37,
      "volume": 55685
    },
    {
      "id": 51,
      "length": 12,
      "width": 20,
      "height": 47,
      "volume": 11280
    },
    {
      "id": 52,
      "length": 23,
      "width": 35,
      "height": 30,
      "volume": 24150
    },
    {
      "id": 53,
      "length": 48,
      "width": 39,
      "height": 17,
      "volume": 31824
    },
    {
      "id": 54,
      "length": 29,
      "width": 41,
      "height": 31,
      "volume": 36859
    },
    {
      "id": 55,
      "length": 16,
      "width": 18,
      "height": 10,
      "volume": 2880
    },
    {
      "id": 56,
      "length": 38,
      "width": 17,
      "height": 13,
      "volume": 8398
    },
    {
      "id": 57,
      "length": 44,
      "width": 12,
      "height": 49,
      "volume": 25872
    },
    {
      "id": 58,
      "length": 16,
      "width": 36,
      "height": 10,
      "volume": 5760
    },
    {
      "id": 59,
      "length": 36,
      "width": 25,
      "height": 47,
      "volume": 42300
    },
    {
      "id": 60,
      "length": 16,
      "width": 32,
      "height": 20,
      "volume": 10240
    },
    {
      "id": 61,
      "length": 42,
      "width": 45,
      "height": 46,
      "volume": 86940
    },
    {
      "id": 62,
      "length": 26,
      "width": 44,
      "height": 14,
      "volume": 16016
    },
    {
      "id": 63,
      "length": 41,
      "width": 12,
      "height": 44,
      "volume": 21648
    },
    {
      "id": 64,
      "length": 23,
      "width": 40,
      "height": 40,
      "volume": 36800
    },
    {
      "id": 65,
      "length": 26,
      "width": 33,
      "height": 32,
      "volume": 27456
    },
    {
      "id": 66,
      "length": 27,
      "width": 23,
      "height": 24,
      "volume": 14904
    },
    {
      "id": 67,
      "length": 24,
      "width": 15,
      "height": 36,
      "volume": 12960
    },
    {
      "id": 68,
      "length": 24,
      "width": 45,
      "height": 17,
      "volume": 18360
    },
    {
      "id": 69,
      "length": 24,
      "width": 12,
      "height": 22,
      "volume": 6336
    },
    {
      "id": 70,
      "length": 43,
      "width": 33,
      "height": 49,
      "volume": 69531
    },
    {
      "id": 71,
      "length": 41,
      "width": 41,
      "height": 39,
      "volume": 65559
    },
    {
      "id": 72,
      "length": 22,
      "width": 10,
      "height": 43,
      "volume": 9460
    },
    {
      "id": 73,
      "length": 24,
      "width": 23,
      "height": 38,
      "volume": 20976
    },
    {
      "id": 74,
      "length": 43,
      "width": 27,
      "height": 16,
      "volume": 18576
    },
    {
      "id": 75,
      "length": 38,
      "width": 40,
      "height": 34,
      "volume": 51680
    },
    {
      "id": 76,
      "length": 47,
      "width": 23,
      "height": 17,
      "volume": 18377
    },
    {
      "id": 77,
      "length": 36,
      "width": 11,
      "height": 26,
      "volume": 10296
    },
    {
      "id": 78,
      "length": 46,
      "width": 23,
      "height": 34,
      "volume": 35972
    },
    {
      "id": 79,
      "length": 39,
      "width": 38,
      "height": 29,
      "volume": 42978
    },
    {
      "id": 80,
      "length": 30,
      "width": 31,
      "height": 44,
      "volume": 40920
    },
    {
      "id": 81,
      "length": 46,
      "width": 25,
      "height": 26,
      "volume": 29900
    },
    {
      "id": 82,
      "length": 25,
      "width": 11,
      "height": 13,
      "volume": 3575
    },
    {
      "id": 83,
      "length": 30,
      "width": 48,
      "height": 43,
      "volume": 61920
    },
    {
      "id": 84,
      "length": 39,
      "width": 15,
      "height": 26,
      "volume": 15210
    },
    {
      "id": 85,
      "length": 48,
      "width": 34,
      "height": 14,
      "volume": 22848
    },
    {
      "id": 86,
      "length": 14,
      "width": 29,
      "height": 25,
      "volume": 10150
    },
    {
      "id": 87,
      "length": 46,
      "width": 49,
      "height": 18,
      "volume": 40572
    },
    {
      "id": 88,
      "length": 14,
      "width": 11,
      "height": 18,
      "volume": 2772
    },
    {
      "id": 89,
      "length": 45,
      "width": 31,
      "height": 31,
      "volume": 43245
    },
    {
      "id": 90,
      "length": 31,
      "width": 43,
      "height": 38,
      "volume": 50654
    },
    {
      "id": 91,
      "length": 47,
      "width": 42,
      "height": 27,
      "volume": 53298
    },
    {
      "id": 92,
      "length": 16,
      "width": 10,
      "height": 42,
      "volume": 6720
    },
    {
      "id": 93,
      "length": 10,
      "width": 33,
      "height": 13,
      "volume": 4290
    },
    {
      "id": 94,
      "length": 13,
      "width": 27,
      "height": 36,
      "volume": 12636
    },
    {
      "id": 95,
      "length": 41,
      "width": 42,
      "height": 37,
      "volume": 63714
    },
    {
      "id": 96,
      "length": 45,
      "width": 15,
      "height": 25,
      "volume": 16875
    },
    {
      "id": 97,
      "length": 43,
      "width": 32,
      "height": 33,
      "volume": 45408
    },
    {
      "id": 98,
      "length": 22,
      "width": 27,
      "height": 22,
      "volume": 13068
    },
    {
      "id": 99,
      "length": 46,
      "width": 48,
      "height": 26,
      "volume": 57408
    },
    {
      "id": 100,
      "length": 24,
      "width": 27,
      "height": 32,
      "volume": 20736
    },
    {
      "id": 101,
      "length": 39,
      "width": 43,
      "height": 13,
      "volume": 21801
    },
    {
      "id": 102,
      "length": 12,
      "width": 16,
      "height": 27,
      "volume": 5184
    },
    {
      "id": 103,
      "length": 16,
      "width": 49,
      "height": 15,
      "volume": 11760
    },
    {
      "id": 104,
      "length": 31,
      "width": 10,
      "height": 13,
      "volume": 4030
    },
    {
      "id": 105,
      "length": 38,
      "width": 30,
      "height": 35,
      "volume": 39900
    },
    {
      "id": 106,
      "length": 23,
      "width": 18,
      "height": 21,
      "volume": 8694
    },
    {
      "id": 107,
      "length": 15,
      "width": 29,
      "height": 33,
      "volume": 14355
    },
    {
      "id": 108,
      "length": 36,
      "width": 47,
      "height": 17,
      "volume": 28764
    },
    {
      "id": 109,
      "length": 10,
      "width": 33,
      "height": 16,
      "volume": 5280
    },
    {
      "id": 110,
      "length": 28,
      "width": 31,
      "height": 44,
      "volume": 38192
    },
    {
      "id": 111,
      "length": 39,
      "width": 38,
      "height": 31,
      "volume": 45942
    },
    {
      "id": 112,
      "length": 20,
      "width": 29,
      "height": 38,
      "volume": 22040
    },
    {
      "id": 113,
      "length": 43,
      "width": 10,
      "height": 40,
      "volume": 17200
    },
    {
      "id": 114,
      "length": 39,
      "width": 27,
      "height": 26,
      "volume": 27378
    },
    {
      "id": 115,
      "length": 47,
      "width": 23,
      "height": 32,
      "volume": 34592
    },
    {
      "id": 116,
      "length": 34,
      "width": 24,
      "height": 31,
      "volume": 25296
    },
    {
      "id": 117,
      "length": 12,
      "width": 28,
      "height": 43,
      "volume": 14448
    },
    {
      "id": 118,
      "length": 44,
      "width": 10,
      "height": 30,
      "volume": 13200
    },
    {
      "id": 119,
      "length": 38,
      "width": 15,
      "height": 46,
      "volume": 26220
    },
    {
      "id": 120,
      "length": 10,
      "width": 10,
      "height": 36,
      "volume": 3600
    },
    {
      "id": 121,
      "length": 30,
      "width": 25,
      "height": 49,
      "volume": 36750
    },
    {
      "id": 122,
      "length": 35,
      "width": 25,
      "height": 37,
      "volume": 32375
    },
    {
      "id": 123,
      "length": 10,
      "width": 45,
      "height": 19,
      "volume": 8550
    },
    {
      "id": 124,
      "length": 26,
      "width": 32,
      "height": 16,
      "volume": 13312
    },
    {
      "id": 125,
      "length": 16,
      "width": 24,
      "height": 43,
      "volume": 16512
    },
    {
      "id": 126,
      "length": 13,
      "width": 23,
      "height": 23,
      "volume": 6877
    },
    {
      "id": 127,
      "length": 25,
      "width": 16,
      "height": 41,
      "volume": 16400
    },
    {
      "id": 128,
      "length": 28,
      "width": 11,
      "height": 19,
      "volume": 5852
    },
    {
      "id": 129,
      "length": 26,
      "width": 46,
      "height": 21,
      "volume": 25116
    },
    {
      "id": 130,
      "length": 15,
      "width": 31,
      "height": 41,
      "volume": 19065
    },
    {
      "id": 131,
      "length": 29,
      "width": 10,
      "height": 15,
      "volume": 4350
    },
    {
      "id": 132,
      "length": 28,
      "width": 27,
      "height": 15,
      "volume": 11340
    },
    {
      "id": 133,
      "length": 42,
      "width": 32,
      "height": 32,
      "volume": 43008
    },
    {
      "id": 134,
      "length": 35,
      "width": 22,
      "height": 16,
      "volume": 12320
    },
    {
      "id": 135,
      "length": 24,
      "width": 36,
      "height": 35,
      "volume": 30240
    },
    {
      "id": 136,
      "length": 42,
      "width": 24,
      "height": 45,
      "volume": 45360
    },
    {
      "id": 137,
      "length": 36,
      "width": 14,
      "height": 11,
      "volume": 5544
    },
    {
      "id": 138,
      "length": 42,
      "width": 25,
      "height": 32,
      "volume": 33600
    },
    {
      "id": 139,
      "length": 47,
      "width": 25,
      "height": 23,
      "volume": 27025
    },
    {
      "id": 140,
      "length": 38,
      "width": 35,
      "height": 44,
      "volume": 58520
    },
    {
      "id": 141,
      "length": 24,
      "width": 12,
      "height": 32,
      "volume": 9216
    },
    {
      "id": 142,
      "length": 38,
      "width": 43,
      "height": 42,
      "volume": 68628
    },
    {
      "id": 143,
      "length": 32,
      "width": 16,
      "height": 12,
      "volume": 6144
    },
    {
      "id": 144,
      "length": 41,
      "width": 40,
      "height": 27,
      "volume": 44280
    },
    {
      "id": 145,
      "length": 16,
      "width": 10,
      "height": 23,
      "volume": 3680
    },
    {
      "id": 146,
      "length": 41,
      "width": 15,
      "height": 48,
      "volume": 29520
    },
    {
      "id": 147,
      "length": 19,
      "width": 16,
      "height": 35,
      "volume": 10640
    },
    {
      "id": 148,
      "length": 43,
      "width": 39,
      "height": 45,
      "volume": 75465
    },
    {
      "id": 149,
      "length": 30,
      "width": 26,
      "height": 42,
      "volume": 32760
    },
    {
      "id": 150,
      "length": 19,
      "width": 21,
      "height": 25,
      "volume": 9975
    },
    {
      "id": 151,
      "length": 41,
      "width": 24,
      "height": 36,
      "volume": 35424
    },
    {
      "id": 152,
      "length": 37,
      "width": 26,
      "height": 11,
      "volume": 10582
    },
    {
      "id": 153,
      "length": 45,
      "width": 16,
      "height": 22,
      "volume": 15840
    },
    {
      "id": 154,
      "length": 24,
      "width": 34,
      "height": 32,
      "volume": 26112
    },
    {
      "id": 155,
      "length": 31,
      "width": 35,
      "height": 42,
      "volume": 45570
    },
    {
      "id": 156,
      "length": 20,
      "width": 19,
      "height": 34,
      "volume": 12920
    },
    {
      "id": 157,
      "length": 46,
      "width": 47,
      "height": 33,
      "volume": 71346
    },
    {
      "id": 158,
      "length": 49,
      "width": 42,
      "height": 26,
      "volume": 53508
    },
    {
      "id": 159,
      "length": 33,
      "width": 46,
      "height": 11,
      "volume": 16698
    },
    {
      "id": 160,
      "length": 41,
      "width": 33,
      "height": 18,
      "volume": 24354
    },
    {
      "id": 161,
      "length": 13,
      "width": 26,
      "height": 26,
      "volume": 8788
    },
    {
      "id": 162,
      "length": 39,
      "width": 49,
      "height": 20,
      "volume": 38220
    },
    {
      "id": 163,
      "length": 30,
      "width": 30,
      "height": 27,
      "volume": 24300
    },
    {
      "id": 164,
      "length": 38,
      "width": 33,
      "height": 19,
      "volume": 23826
    },
    {
      "id": 165,
      "length": 26,
      "width": 27,
      "height": 29,
      "volume": 20358
    },
    {
      "id": 166,
      "length": 46,
      "width": 27,
      "height": 26,
      "volume": 32292
    },
    {
      "id": 167,
      "length": 18,
      "width": 23,
      "height": 38,
      "volume": 15732
    },
    {
      "id": 168,
      "length": 40,
      "width": 13,
      "height": 27,
      "volume": 14040
    },
    {
      "id": 169,
      "length": 29,
      "width": 18,
      "height": 22,
      "volume": 11484
    },
    {
      "id": 170,
      "length": 24,
      "width": 36,
      "height": 24,
      "volume": 20736
    },
    {
      "id": 171,
      "length": 37,
      "width": 46,
      "height": 28,
      "volume": 47656
    },
    {
      "id": 172,
      "length": 35,
      "width": 35,
      "height": 34,
      "volume": 41650
    },
    {
      "id": 173,
      "length": 35,
      "width": 35,
      "height": 37,
      "volume": 45325
    },
    {
      "id": 174,
      "length": 27,
      "width": 41,
      "height": 12,
      "volume": 13284
    },
    {
      "id": 175,
      "length": 11,
      "width": 42,
      "height": 28,
      "volume": 12936
    },
    {
      "id": 176,
      "length": 26,
      "width": 42,
      "height": 21,
      "volume": 22932
    },
    {
      "id": 177,
      "length": 12,
      "width": 35,
      "height": 44,
      "volume": 18480
    },
    {
      "id": 178,
      "length": 17,
      "width": 45,
      "height": 16,
      "volume": 12240
    },
    {
      "id": 179,
      "length": 45,
      "width": 25,
      "height": 33,
      "volume": 37125
    },
    {
      "id": 180,
      "length": 10,
      "width": 34,
      "height": 19,
      "volume": 6460
    },
    {
      "id": 181,
      "length": 25,
      "width": 25,
      "height": 17,
      "volume": 10625
    },
    {
      "id": 182,
      "length": 38,
      "width": 48,
      "height": 37,
      "volume": 67488
    },
    {
      "id": 183,
      "length": 15,
      "width": 25,
      "height": 29,
      "volume": 10875
    },
    {
      "id": 184,
      "length": 25,
      "width": 16,
      "height": 23,
      "volume": 9200
    },
    {
      "id": 185,
      "length": 35,
      "width": 35,
      "height": 23,
      "volume": 28175
    },
    {
      "id": 186,
      "length": 16,
      "width": 42,
      "height": 35,
      "volume": 23520
    },
    {
      "id": 187,
      "length": 29,
      "width": 12,
      "height": 13,
      "volume": 4524
    },
    {
      "id": 188,
      "length": 35,
      "width": 20,
      "height": 11,
      "volume": 7700
    },
    {
      "id": 189,
      "length": 23,
      "width": 39,
      "height": 21,
      "volume": 18837
    },
    {
      "id": 190,
      "length": 35,
      "width": 42,
      "height": 22,
      "volume": 32340
    },
    {
      "id": 191,
      "length": 23,
      "width": 33,
      "height": 43,
      "volume": 32637
    },
    {
      "id": 192,
      "length": 35,
      "width": 30,
      "height": 37,
      "volume": 38850
    },
    {
      "id": 193,
      "length": 45,
      "width": 49,
      "height": 11,
      "volume": 24255
    },
    {
      "id": 194,
      "length": 18,
      "width": 32,
      "height": 24,
      "volume": 13824
    },
    {
      "id": 195,
      "length": 22,
      "width": 32,
      "height": 26,
      "volume": 18304
    },
    {
      "id": 196,
      "length": 11,
      "width": 29,
      "height": 29,
      "volume": 9251
    },
    {
      "id": 197,
      "length": 12,
      "width": 21,
      "height": 49,
      "volume": 12348
    },
    {
      "id": 198,
      "length": 11,
      "width": 45,
      "height": 23,
      "volume": 11385
    },
    {
      "id": 199,
      "length": 25,
      "width": 28,
      "height": 43,
      "volume": 30100
    },
    {
      "id": 200,
      "length": 15,
      "width": 22,
      "height": 45,
      "volume": 14850
    },
    {
      "id": 201,
      "length": 31,
      "width": 27,
      "height": 21,
      "volume": 17577
    },
    {
      "id": 202,
      "length": 39,
      "width": 49,
      "height": 16,
      "volume": 30576
    },
    {
      "id": 203,
      "length": 41,
      "width": 28,
      "height": 15,
      "volume": 17220
    },
    {
      "id": 204,
      "length": 29,
      "width": 36,
      "height": 46,
      "volume": 48024
    },
    {
      "id": 205,
      "length": 16,
      "width": 14,
      "height": 20,
      "volume": 4480
    },
    {
      "id": 206,
      "length": 24,
      "width": 12,
      "height": 14,
      "volume": 4032
    },
    {
      "id": 207,
      "length": 32,
      "width": 46,
      "height": 18,
      "volume": 26496
    },
    {
      "id": 208,
      "length": 24,
      "width": 12,
      "height": 38,
      "volume": 10944
    },
    {
      "id": 209,
      "length": 15,
      "width": 26,
      "height": 35,
      "volume": 13650
    },
    {
      "id": 210,
      "length": 30,
      "width": 17,
      "height": 30,
      "volume": 15300
    },
    {
      "id": 211,
      "length": 20,
      "width": 47,
      "height": 17,
      "volume": 15980
    },
    {
      "id": 212,
      "length": 33,
      "width": 44,
      "height": 23,
      "volume": 33396
    },
    {
      "id": 213,
      "length": 23,
      "width": 19,
      "height": 21,
      "volume": 9177
    },
    {
      "id": 214,
      "length": 47,
      "width": 43,
      "height": 19,
      "volume": 38399
    },
    {
      "id": 215,
      "length": 26,
      "width": 26,
      "height": 12,
      "volume": 8112
    },
    {
      "id": 216,
      "length": 40,
      "width": 10,
      "height": 21,
      "volume": 8400
    },
    {
      "id": 217,
      "length": 48,
      "width": 13,
      "height": 22,
      "volume": 13728
    },
    {
      "id": 218,
      "length": 43,
      "width": 30,
      "height": 31,
      "volume": 39990
    },
    {
      "id": 219,
      "length": 13,
      "width": 27,
      "height": 14,
      "volume": 4914
    },
    {
      "id": 220,
      "length": 28,
      "width": 11,
      "height": 21,
      "volume": 6468
    },
    {
      "id": 221,
      "length": 26,
      "width": 19,
      "height": 43,
      "volume": 21242
    },
    {
      "id": 222,
      "length": 15,
      "width": 17,
      "height": 20,
      "volume": 5100
    },
    {
      "id": 223,
      "length": 21,
      "width": 18,
      "height": 11,
      "volume": 4158
    },
    {
      "id": 224,
      "length": 17,
      "width": 20,
      "height": 45,
      "volume": 15300
    },
    {
      "id": 225,
      "length": 19,
      "width": 30,
      "height": 29,
      "volume": 16530
    },
    {
      "id": 226,
      "length": 17,
      "width": 45,
      "height": 38,
      "volume": 29070
    },
    {
      "id": 227,
      "length": 21,
      "width": 23,
      "height": 30,
      "volume": 14490
    },
    {
      "id": 228,
      "length": 31,
      "width": 30,
      "height": 39,
      "volume": 36270
    },
    {
      "id": 229,
      "length": 48,
      "width": 29,
      "height": 33,
      "volume": 45936
    },
    {
      "id": 230,
      "length": 32,
      "width": 16,
      "height": 18,
      "volume": 9216
    },
    {
      "id": 231,
      "length": 10,
      "width": 35,
      "height": 47,
      "volume": 16450
    },
    {
      "id": 232,
      "length": 47,
      "width": 31,
      "height": 19,
      "volume": 27683
    },
    {
      "id": 233,
      "length": 15,
      "width": 26,
      "height": 47,
      "volume": 18330
    },
    {
      "id": 234,
      "length": 33,
      "width": 19,
      "height": 17,
      "volume": 10659
    },
    {
      "id": 235,
      "length": 30,
      "width": 15,
      "height": 30,
      "volume": 13500
    },
    {
      "id": 236,
      "length": 48,
      "width": 33,
      "height": 42,
      "volume": 66528
    },
    {
      "id": 237,
      "length": 27,
      "width": 37,
      "height": 41,
      "volume": 40959
    },
    {
      "id": 238,
      "length": 21,
      "width": 36,
      "height": 19,
      "volume": 14364
    },
    {
      "id": 239,
      "length": 41,
      "width": 35,
      "height": 34,
      "volume": 48790
    },
    {
      "id": 240,
      "length": 20,
      "width": 32,
      "height": 43,
      "volume": 27520
    },
    {
      "id": 241,
      "length": 49,
      "width": 32,
      "height": 38,
      "volume": 59584
    },
    {
      "id": 242,
      "length": 40,
      "width": 16,
      "height": 49,
      "volume": 31360
    },
    {
      "id": 243,
      "length": 42,
      "width": 30,
      "height": 11,
      "volume": 13860
    },
    {
      "id": 244,
      "length": 27,
      "width": 42,
      "height": 46,
      "volume": 52164
    },
    {
      "id": 245,
      "length": 43,
      "width": 29,
      "height": 44,
      "volume": 54868
    },
    {
      "id": 246,
      "length": 27,
      "width": 33,
      "height": 17,
      "volume": 15147
    },
    {
      "id": 247,
      "length": 39,
      "width": 19,
      "height": 32,
      "volume": 23712
    },
    {
      "id": 248,
      "length": 20,
      "width": 11,
      "height": 35,
      "volume": 7700
    },
    {
      "id": 249,
      "length": 45,
      "width": 42,
      "height": 22,
      "volume": 41580
    },
    {
      "id": 250,
      "length": 49,
      "width": 34,
      "height": 13,
      "volume": 21658
    },
    {
      "id": 251,
      "length": 28,
      "width": 27,
      "height": 46,
      "volume": 34776
    },
    {
      "id": 252,
      "length": 39,
      "width": 28,
      "height": 32,
      "volume": 34944
    },
    {
      "id": 253,
      "length": 25,
      "width": 10,
      "height": 21,
      "volume": 5250
    },
    {
      "id": 254,
      "length": 33,
      "width": 43,
      "height": 17,
      "volume": 24123
    },
    {
      "id": 255,
      "length": 27,
      "width": 14,
      "height": 35,
      "volume": 13230
    },
    {
      "id": 256,
      "length": 39,
      "width": 22,
      "height": 28,
      "volume": 24024
    },
    {
      "id": 257,
      "length": 38,
      "width": 12,
      "height": 35,
      "volume": 15960
    },
    {
      "id": 258,
      "length": 49,
      "width": 21,
      "height": 11,
      "volume": 11319
    },
    {
      "id": 259,
      "length": 20,
      "width": 37,
      "height": 27,
      "volume": 19980
    },
    {
      "id": 260,
      "length": 22,
      "width": 46,
      "height": 31,
      "volume": 31372
    },
    {
      "id": 261,
      "length": 21,
      "width": 11,
      "height": 46,
      "volume": 10626
    },
    {
      "id": 262,
      "length": 16,
      "width": 35,
      "height": 35,
      "volume": 19600
    },
    {
      "id": 263,
      "length": 33,
      "width": 21,
      "height": 25,
      "volume": 17325
    },
    {
      "id": 264,
      "length": 32,
      "width": 49,
      "height": 18,
      "volume": 28224
    },
    {
      "id": 265,
      "length": 41,
      "width": 24,
      "height": 46,
      "volume": 45264
    },
    {
      "id": 266,
      "length": 22,
      "width": 14,
      "height": 20,
      "volume": 6160
    },
    {
      "id": 267,
      "length": 19,
      "width": 22,
      "height": 24,
      "volume": 10032
    },
    {
      "id": 268,
      "length": 16,
      "width": 49,
      "height": 37,
      "volume": 29008
    },
    {
      "id": 269,
      "length": 41,
      "width": 44,
      "height": 24,
      "volume": 43296
    },
    {
      "id": 270,
      "length": 45,
      "width": 30,
      "height": 15,
      "volume": 20250
    },
    {
      "id": 271,
      "length": 10,
      "width": 13,
      "height": 20,
      "volume": 2600
    },
    {
      "id": 272,
      "length": 35,
      "width": 46,
      "height": 32,
      "volume": 51520
    },
    {
      "id": 273,
      "length": 38,
      "width": 30,
      "height": 36,
      "volume": 41040
    },
    {
      "id": 274,
      "length": 48,
      "width": 49,
      "height": 22,
      "volume": 51744
    },
    {
      "id": 275,
      "length": 32,
      "width": 25,
      "height": 39,
      "volume": 31200
    },
    {
      "id": 276,
      "length": 13,
      "width": 49,
      "height": 25,
      "volume": 15925
    },
    {
      "id": 277,
      "length": 40,
      "width": 34,
      "height": 21,
      "volume": 28560
    },
    {
      "id": 278,
      "length": 35,
      "width": 46,
      "height": 42,
      "volume": 67620
    },
    {
      "id": 279,
      "length": 37,
      "width": 18,
      "height": 21,
      "volume": 13986
    },
    {
      "id": 280,
      "length": 14,
      "width": 37,
      "height": 44,
      "volume": 22792
    },
    {
      "id": 281,
      "length": 14,
      "width": 43,
      "height": 43,
      "volume": 25886
    },
    {
      "id": 282,
      "length": 22,
      "width": 48,
      "height": 23,
      "volume": 24288
    },
    {
      "id": 283,
      "length": 20,
      "width": 47,
      "height": 13,
      "volume": 12220
    },
    {
      "id": 284,
      "length": 42,
      "width": 16,
      "height": 17,
      "volume": 11424
    },
    {
      "id": 285,
      "length": 46,
      "width": 19,
      "height": 24,
      "volume": 20976
    },
    {
      "id": 286,
      "length": 47,
      "width": 24,
      "height": 14,
      "volume": 15792
    },
    {
      "id": 287,
      "length": 38,
      "width": 28,
      "height": 19,
      "volume": 20216
    },
    {
      "id": 288,
      "length": 21,
      "width": 13,
      "height": 40,
      "volume": 10920
    },
    {
      "id": 289,
      "length": 27,
      "width": 25,
      "height": 49,
      "volume": 33075
    },
    {
      "id": 290,
      "length": 45,
      "width": 34,
      "height": 32,
      "volume": 48960
    },
    {
      "id": 291,
      "length": 21,
      "width": 43,
      "height": 45,
      "volume": 40635
    },
    {
      "id": 292,
      "length": 46,
      "width": 12,
      "height": 18,
      "volume": 9936
    },
    {
      "id": 293,
      "length": 27,
      "width": 44,
      "height": 43,
      "volume": 51084
    },
    {
      "id": 294,
      "length": 23,
      "width": 13,
      "height": 38,
      "volume": 11362
    },
    {
      "id": 295,
      "length": 24,
      "width": 37,
      "height": 25,
      "volume": 22200
    },
    {
      "id": 296,
      "length": 21,
      "width": 14,
      "height": 43,
      "volume": 12642
    },
    {
      "id": 297,
      "length": 10,
      "width": 48,
      "height": 41,
      "volume": 19680
    },
    {
      "id": 298,
      "length": 35,
      "width": 26,
      "height": 36,
      "volume": 32760
    },
    {
      "id": 299,
      "length": 33,
      "width": 44,
      "height": 48,
      "volume": 69696
    },
    {
      "id": 300,
      "length": 35,
      "width": 47,
      "height": 32,
      "volume": 52640
    },
    {
      "id": 301,
      "length": 31,
      "width": 13,
      "height": 18,
      "volume": 7254
    },
    {
      "id": 302,
      "length": 13,
      "width": 16,
      "height": 32,
      "volume": 6656
    },
    {
      "id": 303,
      "length": 11,
      "width": 33,
      "height": 49,
      "volume": 17787
    },
    {
      "id": 304,
      "length": 40,
      "width": 40,
      "height": 49,
      "volume": 78400
    },
    {
      "id": 305,
      "length": 43,
      "width": 33,
      "height": 35,
      "volume": 49665
    },
    {
      "id": 306,
      "length": 25,
      "width": 22,
      "height": 24,
      "volume": 13200
    },
    {
      "id": 307,
      "length": 36,
      "width": 13,
      "height": 25,
      "volume": 11700
    },
    {
      "id": 308,
      "length": 39,
      "width": 39,
      "height": 45,
      "volume": 68445
    },
    {
      "id": 309,
      "length": 12,
      "width": 31,
      "height": 31,
      "volume": 11532
    },
    {
      "id": 310,
      "length": 21,
      "width": 30,
      "height": 13,
      "volume": 8190
    },
    {
      "id": 311,
      "length": 40,
      "width": 40,
      "height": 32,
      "volume": 51200
    },
    {
      "id": 312,
      "length": 29,
      "width": 24,
      "height": 32,
      "volume": 22272
    },
    {
      "id": 313,
      "length": 37,
      "width": 25,
      "height": 46,
      "volume": 42550
    },
    {
      "id": 314,
      "length": 30,
      "width": 24,
      "height": 26,
      "volume": 18720
    },
    {
      "id": 315,
      "length": 46,
      "width": 22,
      "height": 28,
      "volume": 28336
    },
    {
      "id": 316,
      "length": 39,
      "width": 27,
      "height": 23,
      "volume": 24219
    },
    {
      "id": 317,
      "length": 45,
      "width": 45,
      "height": 29,
      "volume": 58725
    },
    {
      "id": 318,
      "length": 28,
      "width": 16,
      "height": 13,
      "volume": 5824
    },
    {
      "id": 319,
      "length": 43,
      "width": 11,
      "height": 14,
      "volume": 6622
    },
    {
      "id": 320,
      "length": 19,
      "width": 41,
      "height": 22,
      "volume": 17138
    },
    {
      "id": 321,
      "length": 48,
      "width": 14,
      "height": 19,
      "volume": 12768
    },
    {
      "id": 322,
      "length": 19,
      "width": 47,
      "height": 36,
      "volume": 32148
    },
    {
      "id": 323,
      "length": 30,
      "width": 17,
      "height": 10,
      "volume": 5100
    },
    {
      "id": 324,
      "length": 37,
      "width": 48,
      "height": 23,
      "volume": 40848
    },
    {
      "id": 325,
      "length": 30,
      "width": 39,
      "height": 30,
      "volume": 35100
    },
    {
      "id": 326,
      "length": 18,
      "width": 26,
      "height": 14,
      "volume": 6552
    },
    {
      "id": 327,
      "length": 40,
      "width": 49,
      "height": 47,
      "volume": 92120
    },
    {
      "id": 328,
      "length": 28,
      "width": 45,
      "height": 42,
      "volume": 52920
    },
    {
      "id": 329,
      "length": 22,
      "width": 23,
      "height": 42,
      "volume": 21252
    },
    {
      "id": 330,
      "length": 38,
      "width": 45,
      "height": 19,
      "volume": 32490
    },
    {
      "id": 331,
      "length": 40,
      "width": 15,
      "height": 10,
      "volume": 6000
    },
    {
      "id": 332,
      "length": 16,
      "width": 36,
      "height": 30,
      "volume": 17280
    },
    {
      "id": 333,
      "length": 37,
      "width": 25,
      "height": 32,
      "volume": 29600
    },
    {
      "id": 334,
      "length": 29,
      "width": 47,
      "height": 34,
      "volume": 46342
    },
    {
      "id": 335,
      "length": 37,
      "width": 14,
      "height": 30,
      "volume": 15540
    },
    {
      "id": 336,
      "length": 27,
      "width": 15,
      "height": 38,
      "volume": 15390
    },
    {
      "id": 337,
      "length": 28,
      "width": 42,
      "height": 10,
      "volume": 11760
    },
    {
      "id": 338,
      "length": 12,
      "width": 30,
      "height": 44,
      "volume": 15840
    },
    {
      "id": 339,
      "length": 49,
      "width": 12,
      "height": 34,
      "volume": 19992
    },
    {
      "id": 340,
      "length": 47,
      "width": 29,
      "height": 43,
      "volume": 58609
    },
    {
      "id": 341,
      "length": 30,
      "width": 32,
      "height": 15,
      "volume": 14400
    },
    {
      "id": 342,
      "length": 22,
      "width": 32,
      "height": 18,
      "volume": 12672
    },
    {
      "id": 343,
      "length": 26,
      "width": 11,
      "height": 28,
      "volume": 8008
    },
    {
      "id": 344,
      "length": 28,
      "width": 16,
      "height": 29,
      "volume": 12992
    },
    {
      "id": 345,
      "length": 18,
      "width": 26,
      "height": 36,
      "volume": 16848
    },
    {
      "id": 346,
      "length": 11,
      "width": 45,
      "height": 28,
      "volume": 13860
    },
    {
      "id": 347,
      "length": 26,
      "width": 14,
      "height": 48,
      "volume": 17472
    },
    {
      "id": 348,
      "length": 27,
      "width": 16,
      "height": 26,
      "volume": 11232
    },
    {
      "id": 349,
      "length": 48,
      "width": 45,
      "height": 49,
      "volume": 105840
    },
    {
      "id": 350,
      "length": 13,
      "width": 47,
      "height": 34,
      "volume": 20774
    },
    {
      "id": 351,
      "length": 14,
      "width": 39,
      "height": 21,
      "volume": 11466
    },
    {
      "id": 352,
      "length": 13,
      "width": 33,
      "height": 38,
      "volume": 16302
    },
    {
      "id": 353,
      "length": 18,
      "width": 13,
      "height": 33,
      "volume": 7722
    },
    {
      "id": 354,
      "length": 23,
      "width": 14,
      "height": 27,
      "volume": 8694
    },
    {
      "id": 355,
      "length": 28,
      "width": 21,
      "height": 27,
      "volume": 15876
    },
    {
      "id": 356,
      "length": 26,
      "width": 39,
      "height": 33,
      "volume": 33462
    },
    {
      "id": 357,
      "length": 20,
      "width": 44,
      "height": 32,
      "volume": 28160
    },
    {
      "id": 358,
      "length": 26,
      "width": 10,
      "height": 24,
      "volume": 6240
    },
    {
      "id": 359,
      "length": 41,
      "width": 18,
      "height": 24,
      "volume": 17712
    },
    {
      "id": 360,
      "length": 37,
      "width": 33,
      "height": 44,
      "volume": 53724
    },
    {
      "id": 361,
      "length": 31,
      "width": 36,
      "height": 28,
      "volume": 31248
    },
    {
      "id": 362,
      "length": 21,
      "width": 29,
      "height": 10,
      "volume": 6090
    },
    {
      "id": 363,
      "length": 30,
      "width": 10,
      "height": 19,
      "volume": 5700
    },
    {
      "id": 364,
      "length": 41,
      "width": 48,
      "height": 31,
      "volume": 61008
    },
    {
      "id": 365,
      "length": 27,
      "width": 41,
      "height": 36,
      "volume": 39852
    },
    {
      "id": 366,
      "length": 37,
      "width": 27,
      "height": 48,
      "volume": 47952
    },
    {
      "id": 367,
      "length": 38,
      "width": 27,
      "height": 17,
      "volume": 17442
    },
    {
      "id": 368,
      "length": 40,
      "width": 43,
      "height": 16,
      "volume": 27520
    },
    {
      "id": 369,
      "length": 45,
      "width": 27,
      "height": 47,
      "volume": 57105
    },
    {
      "id": 370,
      "length": 18,
      "width": 18,
      "height": 17,
      "volume": 5508
    },
    {
      "id": 371,
      "length": 44,
      "width": 27,
      "height": 14,
      "volume": 16632
    },
    {
      "id": 372,
      "length": 23,
      "width": 37,
      "height": 39,
      "volume": 33189
    },
    {
      "id": 373,
      "length": 13,
      "width": 48,
      "height": 29,
      "volume": 18096
    },
    {
      "id": 374,
      "length": 34,
      "width": 37,
      "height": 21,
      "volume": 26418
    },
    {
      "id": 375,
      "length": 11,
      "width": 23,
      "height": 31,
      "volume": 7843
    },
    {
      "id": 376,
      "length": 40,
      "width": 32,
      "height": 29,
      "volume": 37120
    },
    {
      "id": 377,
      "length": 47,
      "width": 13,
      "height": 24,
      "volume": 14664
    },
    {
      "id": 378,
      "length": 33,
      "width": 34,
      "height": 10,
      "volume": 11220
    },
    {
      "id": 379,
      "length": 16,
      "width": 40,
      "height": 21,
      "volume": 13440
    },
    {
      "id": 380,
      "length": 14,
      "width": 47,
      "height": 21,
      "volume": 13818
    },
    {
      "id": 381,
      "length": 48,
      "width": 27,
      "height": 11,
      "volume": 14256
    },
    {
      "id": 382,
      "length": 19,
      "width": 24,
      "height": 39,
      "volume": 17784
    },
    {
      "id": 383,
      "length": 26,
      "width": 13,
      "height": 16,
      "volume": 5408
    },
    {
      "id": 384,
      "length": 40,
      "width": 48,
      "height": 43,
      "volume": 82560
    },
    {
      "id": 385,
      "length": 15,
      "width": 47,
      "height": 43,
      "volume": 30315
    },
    {
      "id": 386,
      "length": 24,
      "width": 23,
      "height": 15,
      "volume": 8280
    },
    {
      "id": 387,
      "length": 46,
      "width": 41,
      "height": 12,
      "volume": 22632
    },
    {
      "id": 388,
      "length": 12,
      "width": 31,
      "height": 31,
      "volume": 11532
    },
    {
      "id": 389,
      "length": 19,
      "width": 12,
      "height": 21,
      "volume": 4788
    },
    {
      "id": 390,
      "length": 38,
      "width": 26,
      "height": 16,
      "volume": 15808
    },
    {
      "id": 391,
      "length": 22,
      "width": 11,
      "height": 13,
      "volume": 3146
    },
    {
      "id": 392,
      "length": 19,
      "width": 48,
      "height": 33,
      "volume": 30096
    },
    {
      "id": 393,
      "length": 26,
      "width": 15,
      "height": 28,
      "volume": 10920
    },
    {
      "id": 394,
      "length": 14,
      "width": 41,
      "height": 19,
      "volume": 10906
    },
    {
      "id": 395,
      "length": 18,
      "width": 36,
      "height": 22,
      "volume": 14256
    },
    {
      "id": 396,
      "length": 28,
      "width": 30,
      "height": 33,
      "volume": 27720
    },
    {
      "id": 397,
      "length": 47,
      "width": 13,
      "height": 33,
      "volume": 20163
    },
    {
      "id": 398,
      "length": 44,
      "width": 12,
      "height": 13,
      "volume": 6864
    },
    {
      "id": 399,
      "length": 46,
      "width": 49,
      "height": 44,
      "volume": 99176
    },
    {
      "id": 400,
      "length": 40,
      "width": 34,
      "height": 49,
      "volume": 66640
    },
    {
      "id": 401,
      "length": 22,
      "width": 13,
      "height": 23,
      "volume": 6578
    },
    {
      "id": 402,
      "length": 22,
      "width": 36,
      "height": 15,
      "volume": 11880
    },
    {
      "id": 403,
      "length": 26,
      "width": 45,
      "height": 49,
      "volume": 57330
    },
    {
      "id": 404,
      "length": 44,
      "width": 26,
      "height": 11,
      "volume": 12584
    },
    {
      "id": 405,
      "length": 22,
      "width": 11,
      "height": 37,
      "volume": 8954
    },
    {
      "id": 406,
      "length": 35,
      "width": 31,
      "height": 12,
      "volume": 13020
    },
    {
      "id": 407,
      "length": 44,
      "width": 21,
      "height": 33,
      "volume": 30492
    },
    {
      "id": 408,
      "length": 14,
      "width": 29,
      "height": 48,
      "volume": 19488
    },
    {
      "id": 409,
      "length": 48,
      "width": 22,
      "height": 21,
      "volume": 22176
    },
    {
      "id": 410,
      "length": 22,
      "width": 19,
      "height": 42,
      "volume": 17556
    },
    {
      "id": 411,
      "length": 49,
      "width": 25,
      "height": 44,
      "volume": 53900
    },
    {
      "id": 412,
      "length": 12,
      "width": 14,
      "height": 35,
      "volume": 5880
    },
    {
      "id": 413,
      "length": 20,
      "width": 16,
      "height": 19,
      "volume": 6080
    },
    {
      "id": 414,
      "length": 43,
      "width": 12,
      "height": 17,
      "volume": 8772
    },
    {
      "id": 415,
      "length": 40,
      "width": 20,
      "height": 16,
      "volume": 12800
    },
    {
      "id": 416,
      "length": 11,
      "width": 15,
      "height": 41,
      "volume": 6765
    },
    {
      "id": 417,
      "length": 29,
      "width": 43,
      "height": 25,
      "volume": 31175
    },
    {
      "id": 418,
      "length": 34,
      "width": 21,
      "height": 16,
      "volume": 11424
    },
    {
      "id": 419,
      "length": 48,
      "width": 26,
      "height": 20,
      "volume": 24960
    },
    {
      "id": 420,
      "length": 15,
      "width": 32,
      "height": 36,
      "volume": 17280
    },
    {
      "id": 421,
      "length": 15,
      "width": 47,
      "height": 11,
      "volume": 7755
    },
    {
      "id": 422,
      "length": 31,
      "width": 29,
      "height": 34,
      "volume": 30566
    },
    {
      "id": 423,
      "length": 24,
      "width": 38,
      "height": 17,
      "volume": 15504
    },
    {
      "id": 424,
      "length": 46,
      "width": 42,
      "height": 31,
      "volume": 59892
    },
    {
      "id": 425,
      "length": 14,
      "width": 48,
      "height": 27,
      "volume": 18144
    },
    {
      "id": 426,
      "length": 47,
      "width": 46,
      "height": 39,
      "volume": 84318
    },
    {
      "id": 427,
      "length": 40,
      "width": 19,
      "height": 24,
      "volume": 18240
    },
    {
      "id": 428,
      "length": 27,
      "width": 32,
      "height": 42,
      "volume": 36288
    },
    {
      "id": 429,
      "length": 25,
      "width": 47,
      "height": 44,
      "volume": 51700
    },
    {
      "id": 430,
      "length": 43,
      "width": 37,
      "height": 11,
      "volume": 17501
    },
    {
      "id": 431,
      "length": 39,
      "width": 22,
      "height": 25,
      "volume": 21450
    },
    {
      "id": 432,
      "length": 14,
      "width": 37,
      "height": 48,
      "volume": 24864
    },
    {
      "id": 433,
      "length": 29,
      "width": 33,
      "height": 36,
      "volume": 34452
    },
    {
      "id": 434,
      "length": 39,
      "width": 36,
      "height": 35,
      "volume": 49140
    },
    {
      "id": 435,
      "length": 16,
      "width": 47,
      "height": 14,
      "volume": 10528
    },
    {
      "id": 436,
      "length": 32,
      "width": 37,
      "height": 43,
      "volume": 50912
    },
    {
      "id": 437,
      "length": 24,
      "width": 41,
      "height": 35,
      "volume": 34440
    },
    {
      "id": 438,
      "length": 40,
      "width": 28,
      "height": 18,
      "volume": 20160
    },
    {
      "id": 439,
      "length": 38,
      "width": 48,
      "height": 13,
      "volume": 23712
    },
    {
      "id": 440,
      "length": 12,
      "width": 38,
      "height": 20,
      "volume": 9120
    },
    {
      "id": 441,
      "length": 42,
      "width": 47,
      "height": 20,
      "volume": 39480
    },
    {
      "id": 442,
      "length": 36,
      "width": 42,
      "height": 30,
      "volume": 45360
    },
    {
      "id": 443,
      "length": 48,
      "width": 40,
      "height": 47,
      "volume": 90240
    },
    {
      "id": 444,
      "length": 11,
      "width": 36,
      "height": 45,
      "volume": 17820
    },
    {
      "id": 445,
      "length": 20,
      "width": 27,
      "height": 10,
      "volume": 5400
    },
    {
      "id": 446,
      "length": 44,
      "width": 44,
      "height": 40,
      "volume": 77440
    },
    {
      "id": 447,
      "length": 37,
      "width": 48,
      "height": 10,
      "volume": 17760
    },
    {
      "id": 448,
      "length": 34,
      "width": 47,
      "height": 29,
      "volume": 46342
    },
    {
      "id": 449,
      "length": 12,
      "width": 11,
      "height": 27,
      "volume": 3564
    },
    {
      "id": 450,
      "length": 19,
      "width": 14,
      "height": 18,
      "volume": 4788
    },
    {
      "id": 451,
      "length": 11,
      "width": 43,
      "height": 47,
      "volume": 22231
    },
    {
      "id": 452,
      "length": 40,
      "width": 19,
      "height": 21,
      "volume": 15960
    },
    {
      "id": 453,
      "length": 45,
      "width": 30,
      "height": 15,
      "volume": 20250
    },
    {
      "id": 454,
      "length": 12,
      "width": 19,
      "height": 14,
      "volume": 3192
    },
    {
      "id": 455,
      "length": 35,
      "width": 30,
      "height": 35,
      "volume": 36750
    },
    {
      "id": 456,
      "length": 47,
      "width": 35,
      "height": 17,
      "volume": 27965
    },
    {
      "id": 457,
      "length": 14,
      "width": 24,
      "height": 25,
      "volume": 8400
    },
    {
      "id": 458,
      "length": 10,
      "width": 25,
      "height": 46,
      "volume": 11500
    },
    {
      "id": 459,
      "length": 12,
      "width": 40,
      "height": 22,
      "volume": 10560
    },
    {
      "id": 460,
      "length": 25,
      "width": 30,
      "height": 11,
      "volume": 8250
    },
    {
      "id": 461,
      "length": 36,
      "width": 47,
      "height": 35,
      "volume": 59220
    },
    {
      "id": 462,
      "length": 47,
      "width": 34,
      "height": 20,
      "volume": 31960
    },
    {
      "id": 463,
      "length": 17,
      "width": 17,
      "height": 42,
      "volume": 12138
    },
    {
      "id": 464,
      "length": 16,
      "width": 47,
      "height": 30,
      "volume": 22560
    },
    {
      "id": 465,
      "length": 17,
      "width": 30,
      "height": 29,
      "volume": 14790
    },
    {
      "id": 466,
      "length": 17,
      "width": 40,
      "height": 38,
      "volume": 25840
    },
    {
      "id": 467,
      "length": 18,
      "width": 24,
      "height": 39,
      "volume": 16848
    },
    {
      "id": 468,
      "length": 35,
      "width": 19,
      "height": 38,
      "volume": 25270
    },
    {
      "id": 469,
      "length": 25,
      "width": 45,
      "height": 29,
      "volume": 32625
    },
    {
      "id": 470,
      "length": 46,
      "width": 31,
      "height": 16,
      "volume": 22816
    },
    {
      "id": 471,
      "length": 32,
      "width": 49,
      "height": 38,
      "volume": 59584
    },
    {
      "id": 472,
      "length": 25,
      "width": 47,
      "height": 37,
      "volume": 43475
    },
    {
      "id": 473,
      "length": 47,
      "width": 40,
      "height": 23,
      "volume": 43240
    },
    {
      "id": 474,
      "length": 42,
      "width": 18,
      "height": 36,
      "volume": 27216
    },
    {
      "id": 475,
      "length": 33,
      "width": 22,
      "height": 35,
      "volume": 25410
    },
    {
      "id": 476,
      "length": 38,
      "width": 37,
      "height": 37,
      "volume": 52022
    },
    {
      "id": 477,
      "length": 17,
      "width": 32,
      "height": 38,
      "volume": 20672
    },
    {
      "id": 478,
      "length": 14,
      "width": 16,
      "height": 45,
      "volume": 10080
    },
    {
      "id": 479,
      "length": 36,
      "width": 11,
      "height": 34,
      "volume": 13464
    },
    {
      "id": 480,
      "length": 18,
      "width": 36,
      "height": 10,
      "volume": 6480
    },
    {
      "id": 481,
      "length": 32,
      "width": 19,
      "height": 34,
      "volume": 20672
    },
    {
      "id": 482,
      "length": 12,
      "width": 15,
      "height": 15,
      "volume": 2700
    },
    {
      "id": 483,
      "length": 11,
      "width": 27,
      "height": 32,
      "volume": 9504
    },
    {
      "id": 484,
      "length": 11,
      "width": 21,
      "height": 31,
      "volume": 7161
    },
    {
      "id": 485,
      "length": 46,
      "width": 29,
      "height": 48,
      "volume": 64032
    },
    {
      "id": 486,
      "length": 33,
      "width": 29,
      "height": 10,
      "volume": 9570
    },
    {
      "id": 487,
      "length": 10,
      "width": 26,
      "height": 10,
      "volume": 2600
    },
    {
      "id": 488,
      "length": 39,
      "width": 12,
      "height": 20,
      "volume": 9360
    },
    {
      "id": 489,
      "length": 33,
      "width": 31,
      "height": 35,
      "volume": 35805
    },
    {
      "id": 490,
      "length": 22,
      "width": 10,
      "height": 33,
      "volume": 7260
    },
    {
      "id": 491,
      "length": 19,
      "width": 44,
      "height": 33,
      "volume": 27588
    },
    {
      "id": 492,
      "length": 37,
      "width": 45,
      "height": 25,
      "volume": 41625
    },
    {
      "id": 493,
      "length": 49,
      "width": 25,
      "height": 26,
      "volume": 31850
    },
    {
      "id": 494,
      "length": 24,
      "width": 25,
      "height": 24,
      "volume": 14400
    },
    {
      "id": 495,
      "length": 43,
      "width": 20,
      "height": 10,
      "volume": 8600
    },
    {
      "id": 496,
      "length": 24,
      "width": 35,
      "height": 13,
      "volume": 10920
    },
    {
      "id": 497,
      "length": 14,
      "width": 44,
      "height": 22,
      "volume": 13552
    },
    {
      "id": 498,
      "length": 19,
      "width": 20,
      "height": 27,
      "volume": 10260
    },
    {
      "id": 499,
      "length": 43,
      "width": 48,
      "height": 32,
      "volume": 66048
    },
    {
      "id": 500,
      "length": 16,
      "width": 48,
      "height": 12,
      "volume": 9216
    },
    {
      "id": 501,
      "length": 21,
      "width": 16,
      "height": 35,
      "volume": 11760
    },
    {
      "id": 502,
      "length": 42,
      "width": 46,
      "height": 24,
      "volume": 46368
    },
    {
      "id": 503,
      "length": 11,
      "width": 16,
      "height": 41,
      "volume": 7216
    },
    {
      "id": 504,
      "length": 13,
      "width": 29,
      "height": 45,
      "volume": 16965
    },
    {
      "id": 505,
      "length": 41,
      "width": 37,
      "height": 22,
      "volume": 33374
    },
    {
      "id": 506,
      "length": 10,
      "width": 44,
      "height": 39,
      "volume": 17160
    },
    {
      "id": 507,
      "length": 45,
      "width": 34,
      "height": 25,
      "volume": 38250
    },
    {
      "id": 508,
      "length": 28,
      "width": 10,
      "height": 14,
      "volume": 3920
    },
    {
      "id": 509,
      "length": 31,
      "width": 33,
      "height": 46,
      "volume": 47058
    },
    {
      "id": 510,
      "length": 45,
      "width": 45,
      "height": 13,
      "volume": 26325
    },
    {
      "id": 511,
      "length": 45,
      "width": 27,
      "height": 25,
      "volume": 30375
    },
    {
      "id": 512,
      "length": 27,
      "width": 31,
      "height": 11,
      "volume": 9207
    },
    {
      "id": 513,
      "length": 30,
      "width": 45,
      "height": 48,
      "volume": 64800
    },
    {
      "id": 514,
      "length": 48,
      "width": 38,
      "height": 35,
      "volume": 63840
    },
    {
      "id": 515,
      "length": 30,
      "width": 26,
      "height": 25,
      "volume": 19500
    },
    {
      "id": 516,
      "length": 40,
      "width": 18,
      "height": 40,
      "volume": 28800
    },
    {
      "id": 517,
      "length": 23,
      "width": 46,
      "height": 11,
      "volume": 11638
    },
    {
      "id": 518,
      "length": 23,
      "width": 42,
      "height": 44,
      "volume": 42504
    },
    {
      "id": 519,
      "length": 48,
      "width": 29,
      "height": 11,
      "volume": 15312
    },
    {
      "id": 520,
      "length": 28,
      "width": 46,
      "height": 27,
      "volume": 34776
    },
    {
      "id": 521,
      "length": 25,
      "width": 13,
      "height": 21,
      "volume": 6825
    },
    {
      "id": 522,
      "length": 38,
      "width": 16,
      "height": 23,
      "volume": 13984
    },
    {
      "id": 523,
      "length": 21,
      "width": 44,
      "height": 14,
      "volume": 12936
    },
    {
      "id": 524,
      "length": 26,
      "width": 41,
      "height": 19,
      "volume": 20254
    },
    {
      "id": 525,
      "length": 26,
      "width": 14,
      "height": 18,
      "volume": 6552
    },
    {
      "id": 526,
      "length": 42,
      "width": 45,
      "height": 45,
      "volume": 85050
    },
    {
      "id": 527,
      "length": 27,
      "width": 18,
      "height": 38,
      "volume": 18468
    },
    {
      "id": 528,
      "length": 23,
      "width": 34,
      "height": 24,
      "volume": 18768
    },
    {
      "id": 529,
      "length": 15,
      "width": 38,
      "height": 24,
      "volume": 13680
    },
    {
      "id": 530,
      "length": 38,
      "width": 13,
      "height": 27,
      "volume": 13338
    },
    {
      "id": 531,
      "length": 48,
      "width": 25,
      "height": 20,
      "volume": 24000
    },
    {
      "id": 532,
      "length": 23,
      "width": 12,
      "height": 47,
      "volume": 12972
    },
    {
      "id": 533,
      "length": 27,
      "width": 29,
      "height": 34,
      "volume": 26622
    },
    {
      "id": 534,
      "length": 47,
      "width": 22,
      "height": 13,
      "volume": 13442
    },
    {
      "id": 535,
      "length": 23,
      "width": 42,
      "height": 37,
      "volume": 35742
    },
    {
      "id": 536,
      "length": 46,
      "width": 17,
      "height": 43,
      "volume": 33626
    },
    {
      "id": 537,
      "length": 14,
      "width": 14,
      "height": 40,
      "volume": 7840
    },
    {
      "id": 538,
      "length": 18,
      "width": 41,
      "height": 42,
      "volume": 30996
    },
    {
      "id": 539,
      "length": 12,
      "width": 39,
      "height": 21,
      "volume": 9828
    },
    {
      "id": 540,
      "length": 38,
      "width": 12,
      "height": 35,
      "volume": 15960
    },
    {
      "id": 541,
      "length": 39,
      "width": 18,
      "height": 35,
      "volume": 24570
    },
    {
      "id": 542,
      "length": 11,
      "width": 12,
      "height": 13,
      "volume": 1716
    },
    {
      "id": 543,
      "length": 34,
      "width": 22,
      "height": 48,
      "volume": 35904
    },
    {
      "id": 544,
      "length": 44,
      "width": 32,
      "height": 18,
      "volume": 25344
    },
    {
      "id": 545,
      "length": 11,
      "width": 40,
      "height": 11,
      "volume": 4840
    },
    {
      "id": 546,
      "length": 41,
      "width": 27,
      "height": 22,
      "volume": 24354
    },
    {
      "id": 547,
      "length": 14,
      "width": 19,
      "height": 34,
      "volume": 9044
    },
    {
      "id": 548,
      "length": 43,
      "width": 46,
      "height": 39,
      "volume": 77142
    },
    {
      "id": 549,
      "length": 16,
      "width": 15,
      "height": 12,
      "volume": 2880
    },
    {
      "id": 550,
      "length": 22,
      "width": 12,
      "height": 35,
      "volume": 9240
    },
    {
      "id": 551,
      "length": 33,
      "width": 15,
      "height": 21,
      "volume": 10395
    },
    {
      "id": 552,
      "length": 45,
      "width": 11,
      "height": 20,
      "volume": 9900
    },
    {
      "id": 553,
      "length": 48,
      "width": 43,
      "height": 35,
      "volume": 72240
    },
    {
      "id": 554,
      "length": 27,
      "width": 30,
      "height": 45,
      "volume": 36450
    },
    {
      "id": 555,
      "length": 49,
      "width": 31,
      "height": 39,
      "volume": 59241
    },
    {
      "id": 556,
      "length": 39,
      "width": 17,
      "height": 43,
      "volume": 28509
    },
    {
      "id": 557,
      "length": 18,
      "width": 29,
      "height": 49,
      "volume": 25578
    },
    {
      "id": 558,
      "length": 34,
      "width": 28,
      "height": 14,
      "volume": 13328
    },
    {
      "id": 559,
      "length": 20,
      "width": 24,
      "height": 17,
      "volume": 8160
    },
    {
      "id": 560,
      "length": 28,
      "width": 32,
      "height": 36,
      "volume": 32256
    },
    {
      "id": 561,
      "length": 49,
      "width": 41,
      "height": 35,
      "volume": 70315
    },
    {
      "id": 562,
      "length": 36,
      "width": 28,
      "height": 38,
      "volume": 38304
    },
    {
      "id": 563,
      "length": 48,
      "width": 42,
      "height": 28,
      "volume": 56448
    },
    {
      "id": 564,
      "length": 46,
      "width": 28,
      "height": 42,
      "volume": 54096
    },
    {
      "id": 565,
      "length": 25,
      "width": 32,
      "height": 16,
      "volume": 12800
    },
    {
      "id": 566,
      "length": 35,
      "width": 41,
      "height": 21,
      "volume": 30135
    },
    {
      "id": 567,
      "length": 17,
      "width": 14,
      "height": 37,
      "volume": 8806
    },
    {
      "id": 568,
      "length": 14,
      "width": 35,
      "height": 14,
      "volume": 6860
    },
    {
      "id": 569,
      "length": 31,
      "width": 24,
      "height": 22,
      "volume": 16368
    },
    {
      "id": 570,
      "length": 37,
      "width": 42,
      "height": 32,
      "volume": 49728
    },
    {
      "id": 571,
      "length": 42,
      "width": 27,
      "height": 39,
      "volume": 44226
    },
    {
      "id": 572,
      "length": 35,
      "width": 25,
      "height": 22,
      "volume": 19250
    },
    {
      "id": 573,
      "length": 48,
      "width": 42,
      "height": 35,
      "volume": 70560
    },
    {
      "id": 574,
      "length": 10,
      "width": 47,
      "height": 11,
      "volume": 5170
    },
    {
      "id": 575,
      "length": 15,
      "width": 47,
      "height": 33,
      "volume": 23265
    },
    {
      "id": 576,
      "length": 27,
      "width": 36,
      "height": 17,
      "volume": 16524
    },
    {
      "id": 577,
      "length": 37,
      "width": 19,
      "height": 26,
      "volume": 18278
    },
    {
      "id": 578,
      "length": 38,
      "width": 15,
      "height": 23,
      "volume": 13110
    },
    {
      "id": 579,
      "length": 31,
      "width": 15,
      "height": 35,
      "volume": 16275
    },
    {
      "id": 580,
      "length": 48,
      "width": 21,
      "height": 44,
      "volume": 44352
    },
    {
      "id": 581,
      "length": 23,
      "width": 31,
      "height": 32,
      "volume": 22816
    },
    {
      "id": 582,
      "length": 16,
      "width": 49,
      "height": 34,
      "volume": 26656
    },
    {
      "id": 583,
      "length": 22,
      "width": 30,
      "height": 19,
      "volume": 12540
    },
    {
      "id": 584,
      "length": 18,
      "width": 24,
      "height": 11,
      "volume": 4752
    },
    {
      "id": 585,
      "length": 34,
      "width": 22,
      "height": 43,
      "volume": 32164
    },
    {
      "id": 586,
      "length": 43,
      "width": 44,
      "height": 47,
      "volume": 88924
    },
    {
      "id": 587,
      "length": 12,
      "width": 15,
      "height": 28,
      "volume": 5040
    },
    {
      "id": 588,
      "length": 12,
      "width": 27,
      "height": 48,
      "volume": 15552
    },
    {
      "id": 589,
      "length": 18,
      "width": 21,
      "height": 14,
      "volume": 5292
    },
    {
      "id": 590,
      "length": 12,
      "width": 20,
      "height": 39,
      "volume": 9360
    },
    {
      "id": 591,
      "length": 13,
      "width": 14,
      "height": 10,
      "volume": 1820
    },
    {
      "id": 592,
      "length": 36,
      "width": 37,
      "height": 38,
      "volume": 50616
    },
    {
      "id": 593,
      "length": 27,
      "width": 21,
      "height": 22,
      "volume": 12474
    },
    {
      "id": 594,
      "length": 11,
      "width": 46,
      "height": 25,
      "volume": 12650
    },
    {
      "id": 595,
      "length": 33,
      "width": 44,
      "height": 31,
      "volume": 45012
    },
    {
      "id": 596,
      "length": 45,
      "width": 20,
      "height": 38,
      "volume": 34200
    },
    {
      "id": 597,
      "length": 44,
      "width": 24,
      "height": 40,
      "volume": 42240
    },
    {
      "id": 598,
      "length": 25,
      "width": 19,
      "height": 41,
      "volume": 19475
    },
    {
      "id": 599,
      "length": 11,
      "width": 33,
      "height": 32,
      "volume": 11616
    },
    {
      "id": 600,
      "length": 11,
      "width": 47,
      "height": 40,
      "volume": 20680
    },
    {
      "id": 601,
      "length": 49,
      "width": 35,
      "height": 38,
      "volume": 65170
    },
    {
      "id": 602,
      "length": 12,
      "width": 23,
      "height": 34,
      "volume": 9384
    },
    {
      "id": 603,
      "length": 10,
      "width": 12,
      "height": 35,
      "volume": 4200
    },
    {
      "id": 604,
      "length": 27,
      "width": 18,
      "height": 47,
      "volume": 22842
    },
    {
      "id": 605,
      "length": 32,
      "width": 30,
      "height": 10,
      "volume": 9600
    },
    {
      "id": 606,
      "length": 30,
      "width": 36,
      "height": 15,
      "volume": 16200
    },
    {
      "id": 607,
      "length": 45,
      "width": 37,
      "height": 26,
      "volume": 43290
    },
    {
      "id": 608,
      "length": 49,
      "width": 12,
      "height": 21,
      "volume": 12348
    },
    {
      "id": 609,
      "length": 48,
      "width": 21,
      "height": 11,
      "volume": 11088
    },
    {
      "id": 610,
      "length": 31,
      "width": 32,
      "height": 39,
      "volume": 38688
    },
    {
      "id": 611,
      "length": 14,
      "width": 18,
      "height": 30,
      "volume": 7560
    },
    {
      "id": 612,
      "length": 20,
      "width": 14,
      "height": 44,
      "volume": 12320
    },
    {
      "id": 613,
      "length": 36,
      "width": 11,
      "height": 33,
      "volume": 13068
    },
    {
      "id": 614,
      "length": 40,
      "width": 42,
      "height": 48,
      "volume": 80640
    },
    {
      "id": 615,
      "length": 39,
      "width": 46,
      "height": 37,
      "volume": 66378
    },
    {
      "id": 616,
      "length": 40,
      "width": 20,
      "height": 32,
      "volume": 25600
    },
    {
      "id": 617,
      "length": 11,
      "width": 49,
      "height": 36,
      "volume": 19404
    },
    {
      "id": 618,
      "length": 44,
      "width": 11,
      "height": 48,
      "volume": 23232
    },
    {
      "id": 619,
      "length": 46,
      "width": 30,
      "height": 14,
      "volume": 19320
    },
    {
      "id": 620,
      "length": 30,
      "width": 38,
      "height": 29,
      "volume": 33060
    },
    {
      "id": 621,
      "length": 47,
      "width": 29,
      "height": 34,
      "volume": 46342
    },
    {
      "id": 622,
      "length": 11,
      "width": 41,
      "height": 35,
      "volume": 15785
    },
    {
      "id": 623,
      "length": 15,
      "width": 12,
      "height": 42,
      "volume": 7560
    },
    {
      "id": 624,
      "length": 10,
      "width": 14,
      "height": 22,
      "volume": 3080
    },
    {
      "id": 625,
      "length": 28,
      "width": 21,
      "height": 34,
      "volume": 19992
    },
    {
      "id": 626,
      "length": 44,
      "width": 21,
      "height": 39,
      "volume": 36036
    },
    {
      "id": 627,
      "length": 14,
      "width": 43,
      "height": 31,
      "volume": 18662
    },
    {
      "id": 628,
      "length": 48,
      "width": 22,
      "height": 12,
      "volume": 12672
    },
    {
      "id": 629,
      "length": 29,
      "width": 40,
      "height": 14,
      "volume": 16240
    },
    {
      "id": 630,
      "length": 33,
      "width": 49,
      "height": 42,
      "volume": 67914
    },
    {
      "id": 631,
      "length": 17,
      "width": 33,
      "height": 29,
      "volume": 16269
    },
    {
      "id": 632,
      "length": 25,
      "width": 21,
      "height": 22,
      "volume": 11550
    },
    {
      "id": 633,
      "length": 48,
      "width": 34,
      "height": 41,
      "volume": 66912
    },
    {
      "id": 634,
      "length": 33,
      "width": 18,
      "height": 49,
      "volume": 29106
    },
    {
      "id": 635,
      "length": 32,
      "width": 22,
      "height": 41,
      "volume": 28864
    },
    {
      "id": 636,
      "length": 24,
      "width": 45,
      "height": 14,
      "volume": 15120
    },
    {
      "id": 637,
      "length": 31,
      "width": 25,
      "height": 19,
      "volume": 14725
    },
    {
      "id": 638,
      "length": 33,
      "width": 27,
      "height": 27,
      "volume": 24057
    },
    {
      "id": 639,
      "length": 16,
      "width": 13,
      "height": 35,
      "volume": 7280
    },
    {
      "id": 640,
      "length": 14,
      "width": 25,
      "height": 44,
      "volume": 15400
    },
    {
      "id": 641,
      "length": 35,
      "width": 27,
      "height": 38,
      "volume": 35910
    },
    {
      "id": 642,
      "length": 32,
      "width": 23,
      "height": 24,
      "volume": 17664
    },
    {
      "id": 643,
      "length": 42,
      "width": 34,
      "height": 30,
      "volume": 42840
    },
    {
      "id": 644,
      "length": 26,
      "width": 32,
      "height": 26,
      "volume": 21632
    },
    {
      "id": 645,
      "length": 23,
      "width": 38,
      "height": 29,
      "volume": 25346
    },
    {
      "id": 646,
      "length": 39,
      "width": 28,
      "height": 48,
      "volume": 52416
    },
    {
      "id": 647,
      "length": 22,
      "width": 27,
      "height": 32,
      "volume": 19008
    },
    {
      "id": 648,
      "length": 42,
      "width": 48,
      "height": 49,
      "volume": 98784
    },
    {
      "id": 649,
      "length": 27,
      "width": 18,
      "height": 42,
      "volume": 20412
    },
    {
      "id": 650,
      "length": 41,
      "width": 26,
      "height": 28,
      "volume": 29848
    },
    {
      "id": 651,
      "length": 36,
      "width": 15,
      "height": 44,
      "volume": 23760
    },
    {
      "id": 652,
      "length": 46,
      "width": 43,
      "height": 29,
      "volume": 57362
    },
    {
      "id": 653,
      "length": 34,
      "width": 13,
      "height": 19,
      "volume": 8398
    },
    {
      "id": 654,
      "length": 19,
      "width": 33,
      "height": 30,
      "volume": 18810
    },
    {
      "id": 655,
      "length": 20,
      "width": 36,
      "height": 25,
      "volume": 18000
    },
    {
      "id": 656,
      "length": 35,
      "width": 39,
      "height": 25,
      "volume": 34125
    },
    {
      "id": 657,
      "length": 16,
      "width": 25,
      "height": 44,
      "volume": 17600
    },
    {
      "id": 658,
      "length": 25,
      "width": 49,
      "height": 21,
      "volume": 25725
    },
    {
      "id": 659,
      "length": 44,
      "width": 30,
      "height": 45,
      "volume": 59400
    },
    {
      "id": 660,
      "length": 26,
      "width": 41,
      "height": 15,
      "volume": 15990
    },
    {
      "id": 661,
      "length": 33,
      "width": 36,
      "height": 29,
      "volume": 34452
    },
    {
      "id": 662,
      "length": 34,
      "width": 11,
      "height": 18,
      "volume": 6732
    },
    {
      "id": 663,
      "length": 37,
      "width": 47,
      "height": 12,
      "volume": 20868
    },
    {
      "id": 664,
      "length": 29,
      "width": 15,
      "height": 48,
      "volume": 20880
    },
    {
      "id": 665,
      "length": 42,
      "width": 10,
      "height": 46,
      "volume": 19320
    },
    {
      "id": 666,
      "length": 15,
      "width": 43,
      "height": 24,
      "volume": 15480
    }
  ]
}